MANIFEST.in
TestApp.py
credits.txt
pip-log.txt
setup.py
wsgisvc.py
docs/index.txt
docs/_build/html/_sources/index.txt
test/TestWsgisvc.py
test/testWsgisvc.py
test_ve/tstpkg1/tstpkg.egg-info/SOURCES.txt
test_ve/tstpkg1/tstpkg.egg-info/dependency_links.txt
test_ve/tstpkg1/tstpkg.egg-info/top_level.txt
test_ve/tstpkg2/tstpkg.egg-info/SOURCES.txt
test_ve/tstpkg2/tstpkg.egg-info/dependency_links.txt
test_ve/tstpkg2/tstpkg.egg-info/top_level.txt
test_ve/tstpkgm/tstpkgm.egg-info/SOURCES.txt
test_ve/tstpkgm/tstpkgm.egg-info/dependency_links.txt
test_ve/tstpkgm/tstpkgm.egg-info/requires.txt
test_ve/tstpkgm/tstpkgm.egg-info/top_level.txt
wsgisvc.egg-info/PKG-INFO
wsgisvc.egg-info/SOURCES.txt
wsgisvc.egg-info/dependency_links.txt
wsgisvc.egg-info/entry_points.txt
wsgisvc.egg-info/requires.txt
wsgisvc.egg-info/top_level.txt