Metadata-Version: 1.0
Name: wsgisvc
Version: 0.8.2.0
Summary: A script to install paste deployment configurations as windows services.
Home-page: UNKNOWN
Author: Tibor Arpas
Author-email: tibor.arpas@infinit.sk
License: Apache 2.0
Platform: UNKNOWN
Classifier: Development Status :: 4 - Beta
